setup.py
mpqlock/My_code_lock_2024.cp39-win_amd64.pyd
mpqlock/My_code_lock_2024.py
mpqlock/__init__.py
mpqlock.egg-info/PKG-INFO
mpqlock.egg-info/SOURCES.txt
mpqlock.egg-info/dependency_links.txt
mpqlock.egg-info/requires.txt
mpqlock.egg-info/top_level.txt