Metadata-Version: 2.1
Name: mpqlock
Version: 0.0.11
Summary: lock for MPQ_code
Home-page: https://github.com/miaopeiqi
Author: MPQ
Author-email: miaopeiqi@163.com
License: UNKNOWN
Platform: UNKNOWN
